[
    {
        "url": "https://invidious.f5.si",
        "type": "invidious",
        "score": 85,
        "latency": "1052ms",
        "cors": true,
        "last_updated": "2026-03-21 20:52:16"
    },
    {
        "url": "https://yt.omada.cafe",
        "type": "invidious",
        "score": 70,
        "latency": "2440ms",
        "cors": true,
        "last_updated": "2026-03-21 20:52:13"
    },
    {
        "url": "https://echostreamz.com",
        "type": "invidious",
        "score": 70,
        "latency": "2274ms",
        "cors": true,
        "last_updated": "2026-03-21 20:52:18"
    },
    {
        "url": "https://inv.nadeko.net",
        "type": "invidious",
        "score": 30,
        "latency": "487ms",
        "cors": false,
        "last_updated": "2026-03-21 20:51:49"
    },
    {
        "url": "https://invidious.reallyaweso.me",
        "type": "invidious",
        "score": 30,
        "latency": "386ms",
        "cors": false,
        "last_updated": "2026-03-21 20:52:11"
    },
    {
        "url": "https://invidious.darkness.services",
        "type": "invidious",
        "score": 30,
        "latency": "170ms",
        "cors": false,
        "last_updated": "2026-03-21 20:52:15"
    },
    {
        "url": "https://pipedapi.kavin.rocks",
        "type": "piped",
        "score": 30,
        "latency": "463ms",
        "cors": false,
        "last_updated": "2026-03-21 20:52:19"
    },
    {
        "url": "https://pipedapi.dedyn.io",
        "type": "piped",
        "score": 30,
        "latency": "458ms",
        "cors": false,
        "last_updated": "2026-03-21 20:52:30"
    },
    {
        "url": "https://iv.melmac.space",
        "type": "invidious",
        "score": 15,
        "latency": "661ms",
        "cors": false,
        "last_updated": "2026-03-21 20:51:59"
    },
    {
        "url": "https://invidious.tiekoetter.com",
        "type": "invidious",
        "score": 15,
        "latency": "756ms",
        "cors": false,
        "last_updated": "2026-03-21 20:52:10"
    },
    {
        "url": "https://invidious.nerdvpn.de",
        "type": "invidious",
        "score": 15,
        "latency": "636ms",
        "cors": false,
        "last_updated": "2026-03-21 20:52:14"
    },
    {
        "url": "https://yewtu.be",
        "type": "invidious",
        "score": 15,
        "latency": "735ms",
        "cors": false,
        "last_updated": "2026-03-21 20:52:14"
    },
    {
        "url": "https://invidious.materialio.us",
        "type": "invidious",
        "score": 15,
        "latency": "538ms",
        "cors": false,
        "last_updated": "2026-03-21 20:52:16"
    },
    {
        "url": "https://api.piped.private.coffee",
        "type": "piped",
        "score": 15,
        "latency": "938ms",
        "cors": false,
        "last_updated": "2026-03-21 20:52:20"
    }
]