[
    {
        "url": "https://inv.vern.cc",
        "type": "invidious",
        "score": 70,
        "latency": "4136ms",
        "cors": true,
        "last_updated": "2026-02-12 23:56:09"
    },
    {
        "url": "https://yt.vern.cc",
        "type": "invidious",
        "score": 70,
        "latency": "3463ms",
        "cors": true,
        "last_updated": "2026-02-12 23:56:13"
    },
    {
        "url": "https://yt.omada.cafe",
        "type": "invidious",
        "score": 70,
        "latency": "2474ms",
        "cors": true,
        "last_updated": "2026-02-12 23:56:17"
    },
    {
        "url": "https://pipedapi.kavin.rocks",
        "type": "piped",
        "score": 30,
        "latency": "91ms",
        "cors": false,
        "last_updated": "2026-02-12 23:56:40"
    },
    {
        "url": "https://pipedapi.dedyn.io",
        "type": "piped",
        "score": 30,
        "latency": "480ms",
        "cors": false,
        "last_updated": "2026-02-12 23:56:42"
    },
    {
        "url": "https://inv.nadeko.net",
        "type": "invidious",
        "score": 15,
        "latency": "502ms",
        "cors": false,
        "last_updated": "2026-02-12 23:56:05"
    },
    {
        "url": "https://iv.melmac.space",
        "type": "invidious",
        "score": 15,
        "latency": "936ms",
        "cors": false,
        "last_updated": "2026-02-12 23:56:10"
    },
    {
        "url": "https://invidious.tiekoetter.com",
        "type": "invidious",
        "score": 15,
        "latency": "745ms",
        "cors": false,
        "last_updated": "2026-02-12 23:56:14"
    },
    {
        "url": "https://invidious.reallyaweso.me",
        "type": "invidious",
        "score": 15,
        "latency": "527ms",
        "cors": false,
        "last_updated": "2026-02-12 23:56:15"
    },
    {
        "url": "https://invidious.nerdvpn.de",
        "type": "invidious",
        "score": 15,
        "latency": "619ms",
        "cors": false,
        "last_updated": "2026-02-12 23:56:18"
    },
    {
        "url": "https://yewtu.be",
        "type": "invidious",
        "score": 15,
        "latency": "1047ms",
        "cors": false,
        "last_updated": "2026-02-12 23:56:19"
    },
    {
        "url": "https://invidious.materialio.us",
        "type": "invidious",
        "score": 15,
        "latency": "538ms",
        "cors": false,
        "last_updated": "2026-02-12 23:56:40"
    },
    {
        "url": "https://api.piped.private.coffee",
        "type": "piped",
        "score": 15,
        "latency": "829ms",
        "cors": false,
        "last_updated": "2026-02-12 23:56:41"
    },
    {
        "url": "https://pipedapi.wireway.ch",
        "type": "piped",
        "score": 15,
        "latency": "521ms",
        "cors": false,
        "last_updated": "2026-02-12 23:56:41"
    }
]