[
    {
        "url": "https://yt.omada.cafe",
        "type": "invidious",
        "score": 85,
        "latency": "1018ms",
        "cors": true,
        "last_updated": "2026-05-29 08:41:36"
    },
    {
        "url": "https://api.piped.private.coffee",
        "type": "piped",
        "score": 85,
        "latency": "1294ms",
        "cors": true,
        "last_updated": "2026-05-29 08:41:53"
    },
    {
        "url": "https://echostreamz.com",
        "type": "invidious",
        "score": 70,
        "latency": "2264ms",
        "cors": true,
        "last_updated": "2026-05-29 08:41:51"
    },
    {
        "url": "https://pipedapi.wireway.ch",
        "type": "piped",
        "score": 70,
        "latency": "2581ms",
        "cors": true,
        "last_updated": "2026-05-29 08:41:55"
    },
    {
        "url": "https://pipedapi.dedyn.io",
        "type": "piped",
        "score": 70,
        "latency": "1525ms",
        "cors": true,
        "last_updated": "2026-05-29 08:41:57"
    },
    {
        "url": "https://inv.vern.cc",
        "type": "invidious",
        "score": 30,
        "latency": "439ms",
        "cors": false,
        "last_updated": "2026-05-29 08:41:32"
    },
    {
        "url": "https://yt.vern.cc",
        "type": "invidious",
        "score": 30,
        "latency": "408ms",
        "cors": false,
        "last_updated": "2026-05-29 08:41:33"
    },
    {
        "url": "https://invidious.materialio.us",
        "type": "invidious",
        "score": 30,
        "latency": "422ms",
        "cors": false,
        "last_updated": "2026-05-29 08:41:49"
    },
    {
        "url": "https://inv.nadeko.net",
        "type": "invidious",
        "score": 15,
        "latency": "510ms",
        "cors": false,
        "last_updated": "2026-05-29 08:41:32"
    },
    {
        "url": "https://invidious.tiekoetter.com",
        "type": "invidious",
        "score": 15,
        "latency": "882ms",
        "cors": false,
        "last_updated": "2026-05-29 08:41:34"
    },
    {
        "url": "https://invidious.reallyaweso.me",
        "type": "invidious",
        "score": 15,
        "latency": "759ms",
        "cors": false,
        "last_updated": "2026-05-29 08:41:35"
    },
    {
        "url": "https://yewtu.be",
        "type": "invidious",
        "score": 15,
        "latency": "1152ms",
        "cors": false,
        "last_updated": "2026-05-29 08:41:47"
    },
    {
        "url": "https://invidious.darkness.services",
        "type": "invidious",
        "score": 15,
        "latency": "652ms",
        "cors": false,
        "last_updated": "2026-05-29 08:41:47"
    },
    {
        "url": "https://invidious.f5.si",
        "type": "invidious",
        "score": 15,
        "latency": "855ms",
        "cors": false,
        "last_updated": "2026-05-29 08:41:48"
    },
    {
        "url": "https://pipedapi.kavin.rocks",
        "type": "piped",
        "score": 15,
        "latency": "517ms",
        "cors": false,
        "last_updated": "2026-05-29 08:41:51"
    }
]