[
    {
        "url": "https://pipedapi.wireway.ch",
        "type": "piped",
        "score": 85,
        "latency": "620ms",
        "cors": true,
        "last_updated": "2026-03-02 10:42:57"
    },
    {
        "url": "https://yt.omada.cafe",
        "type": "invidious",
        "score": 70,
        "latency": "1553ms",
        "cors": true,
        "last_updated": "2026-03-02 10:42:52"
    },
    {
        "url": "https://inv.nadeko.net",
        "type": "invidious",
        "score": 30,
        "latency": "424ms",
        "cors": false,
        "last_updated": "2026-03-02 10:42:28"
    },
    {
        "url": "https://invidious.reallyaweso.me",
        "type": "invidious",
        "score": 30,
        "latency": "319ms",
        "cors": false,
        "last_updated": "2026-03-02 10:42:50"
    },
    {
        "url": "https://echostreamz.com",
        "type": "invidious",
        "score": 30,
        "latency": "488ms",
        "cors": false,
        "last_updated": "2026-03-02 10:42:56"
    },
    {
        "url": "https://pipedapi.kavin.rocks",
        "type": "piped",
        "score": 30,
        "latency": "105ms",
        "cors": false,
        "last_updated": "2026-03-02 10:42:56"
    },
    {
        "url": "https://iv.melmac.space",
        "type": "invidious",
        "score": 15,
        "latency": "615ms",
        "cors": false,
        "last_updated": "2026-03-02 10:42:39"
    },
    {
        "url": "https://invidious.tiekoetter.com",
        "type": "invidious",
        "score": 15,
        "latency": "748ms",
        "cors": false,
        "last_updated": "2026-03-02 10:42:50"
    },
    {
        "url": "https://invidious.nerdvpn.de",
        "type": "invidious",
        "score": 15,
        "latency": "557ms",
        "cors": false,
        "last_updated": "2026-03-02 10:42:52"
    },
    {
        "url": "https://yewtu.be",
        "type": "invidious",
        "score": 15,
        "latency": "786ms",
        "cors": false,
        "last_updated": "2026-03-02 10:42:53"
    },
    {
        "url": "https://invidious.f5.si",
        "type": "invidious",
        "score": 15,
        "latency": "1005ms",
        "cors": false,
        "last_updated": "2026-03-02 10:42:54"
    },
    {
        "url": "https://invidious.materialio.us",
        "type": "invidious",
        "score": 15,
        "latency": "546ms",
        "cors": false,
        "last_updated": "2026-03-02 10:42:55"
    },
    {
        "url": "https://api.piped.private.coffee",
        "type": "piped",
        "score": 15,
        "latency": "957ms",
        "cors": false,
        "last_updated": "2026-03-02 10:42:57"
    },
    {
        "url": "https://pipedapi.dedyn.io",
        "type": "piped",
        "score": 15,
        "latency": "777ms",
        "cors": false,
        "last_updated": "2026-03-02 10:42:58"
    }
]