[
    {
        "url": "https://yt.omada.cafe",
        "type": "invidious",
        "score": 85,
        "latency": "1429ms",
        "cors": true,
        "last_updated": "2026-04-22 12:12:45"
    },
    {
        "url": "https://invidious.darkness.services",
        "type": "invidious",
        "score": 85,
        "latency": "1112ms",
        "cors": true,
        "last_updated": "2026-04-22 12:12:49"
    },
    {
        "url": "https://invidious.f5.si",
        "type": "invidious",
        "score": 85,
        "latency": "736ms",
        "cors": true,
        "last_updated": "2026-04-22 12:12:50"
    },
    {
        "url": "https://pipedapi.wireway.ch",
        "type": "piped",
        "score": 85,
        "latency": "724ms",
        "cors": true,
        "last_updated": "2026-04-22 12:12:53"
    },
    {
        "url": "https://pipedapi.dedyn.io",
        "type": "piped",
        "score": 85,
        "latency": "818ms",
        "cors": true,
        "last_updated": "2026-04-22 12:12:54"
    },
    {
        "url": "https://api.piped.private.coffee",
        "type": "piped",
        "score": 70,
        "latency": "1553ms",
        "cors": true,
        "last_updated": "2026-04-22 12:12:52"
    },
    {
        "url": "https://invidious.reallyaweso.me",
        "type": "invidious",
        "score": 30,
        "latency": "481ms",
        "cors": false,
        "last_updated": "2026-04-22 12:12:44"
    },
    {
        "url": "https://invidious.materialio.us",
        "type": "invidious",
        "score": 30,
        "latency": "437ms",
        "cors": false,
        "last_updated": "2026-04-22 12:12:50"
    },
    {
        "url": "https://pipedapi.kavin.rocks",
        "type": "piped",
        "score": 30,
        "latency": "223ms",
        "cors": false,
        "last_updated": "2026-04-22 12:12:51"
    },
    {
        "url": "https://inv.nadeko.net",
        "type": "invidious",
        "score": 15,
        "latency": "558ms",
        "cors": false,
        "last_updated": "2026-04-22 12:12:40"
    },
    {
        "url": "https://inv.vern.cc",
        "type": "invidious",
        "score": 15,
        "latency": "1182ms",
        "cors": false,
        "last_updated": "2026-04-22 12:12:41"
    },
    {
        "url": "https://yt.vern.cc",
        "type": "invidious",
        "score": 15,
        "latency": "1147ms",
        "cors": false,
        "last_updated": "2026-04-22 12:12:43"
    },
    {
        "url": "https://invidious.tiekoetter.com",
        "type": "invidious",
        "score": 15,
        "latency": "971ms",
        "cors": false,
        "last_updated": "2026-04-22 12:12:44"
    },
    {
        "url": "https://invidious.nerdvpn.de",
        "type": "invidious",
        "score": 15,
        "latency": "805ms",
        "cors": false,
        "last_updated": "2026-04-22 12:12:46"
    },
    {
        "url": "https://yewtu.be",
        "type": "invidious",
        "score": 15,
        "latency": "1452ms",
        "cors": false,
        "last_updated": "2026-04-22 12:12:48"
    },
    {
        "url": "https://echostreamz.com",
        "type": "invidious",
        "score": 15,
        "latency": "650ms",
        "cors": false,
        "last_updated": "2026-04-22 12:12:51"
    }
]