[
    {
        "url": "https://api.piped.private.coffee",
        "type": "piped",
        "score": 85,
        "latency": "1200ms",
        "cors": true,
        "last_updated": "2026-07-11 11:29:55"
    },
    {
        "url": "https://pipedapi.wireway.ch",
        "type": "piped",
        "score": 70,
        "latency": "2134ms",
        "cors": true,
        "last_updated": "2026-07-11 11:29:57"
    },
    {
        "url": "https://pipedapi.dedyn.io",
        "type": "piped",
        "score": 70,
        "latency": "3343ms",
        "cors": true,
        "last_updated": "2026-07-11 11:30:01"
    },
    {
        "url": "https://inv.nadeko.net",
        "type": "invidious",
        "score": 30,
        "latency": "433ms",
        "cors": false,
        "last_updated": "2026-07-11 11:29:36"
    },
    {
        "url": "https://inv.vern.cc",
        "type": "invidious",
        "score": 30,
        "latency": "330ms",
        "cors": false,
        "last_updated": "2026-07-11 11:29:36"
    },
    {
        "url": "https://yt.vern.cc",
        "type": "invidious",
        "score": 30,
        "latency": "300ms",
        "cors": false,
        "last_updated": "2026-07-11 11:29:37"
    },
    {
        "url": "https://invidious.reallyaweso.me",
        "type": "invidious",
        "score": 30,
        "latency": "481ms",
        "cors": false,
        "last_updated": "2026-07-11 11:29:38"
    },
    {
        "url": "https://invidious.f5.si",
        "type": "invidious",
        "score": 30,
        "latency": "481ms",
        "cors": false,
        "last_updated": "2026-07-11 11:29:51"
    },
    {
        "url": "https://invidious.materialio.us",
        "type": "invidious",
        "score": 30,
        "latency": "415ms",
        "cors": false,
        "last_updated": "2026-07-11 11:29:52"
    },
    {
        "url": "https://pipedapi.kavin.rocks",
        "type": "piped",
        "score": 30,
        "latency": "469ms",
        "cors": false,
        "last_updated": "2026-07-11 11:29:54"
    },
    {
        "url": "https://invidious.tiekoetter.com",
        "type": "invidious",
        "score": 15,
        "latency": "776ms",
        "cors": false,
        "last_updated": "2026-07-11 11:29:37"
    },
    {
        "url": "https://invidious.nerdvpn.de",
        "type": "invidious",
        "score": 15,
        "latency": "780ms",
        "cors": false,
        "last_updated": "2026-07-11 11:29:49"
    },
    {
        "url": "https://yewtu.be",
        "type": "invidious",
        "score": 15,
        "latency": "1443ms",
        "cors": false,
        "last_updated": "2026-07-11 11:29:50"
    },
    {
        "url": "https://invidious.darkness.services",
        "type": "invidious",
        "score": 15,
        "latency": "759ms",
        "cors": false,
        "last_updated": "2026-07-11 11:29:51"
    }
]