[
    {
        "url": "https://invidious.f5.si",
        "type": "invidious",
        "score": 100,
        "latency": "468ms",
        "cors": true,
        "last_updated": "2026-05-05 20:06:58"
    },
    {
        "url": "https://yt.omada.cafe",
        "type": "invidious",
        "score": 85,
        "latency": "624ms",
        "cors": true,
        "last_updated": "2026-05-05 20:06:55"
    },
    {
        "url": "https://invidious.darkness.services",
        "type": "invidious",
        "score": 85,
        "latency": "787ms",
        "cors": true,
        "last_updated": "2026-05-05 20:06:57"
    },
    {
        "url": "https://api.piped.private.coffee",
        "type": "piped",
        "score": 85,
        "latency": "1379ms",
        "cors": true,
        "last_updated": "2026-05-05 20:07:02"
    },
    {
        "url": "https://echostreamz.com",
        "type": "invidious",
        "score": 70,
        "latency": "1964ms",
        "cors": true,
        "last_updated": "2026-05-05 20:07:00"
    },
    {
        "url": "https://pipedapi.wireway.ch",
        "type": "piped",
        "score": 70,
        "latency": "2045ms",
        "cors": true,
        "last_updated": "2026-05-05 20:07:04"
    },
    {
        "url": "https://pipedapi.dedyn.io",
        "type": "piped",
        "score": 70,
        "latency": "1695ms",
        "cors": true,
        "last_updated": "2026-05-05 20:07:05"
    },
    {
        "url": "https://invidious.materialio.us",
        "type": "invidious",
        "score": 30,
        "latency": "408ms",
        "cors": false,
        "last_updated": "2026-05-05 20:06:58"
    },
    {
        "url": "https://pipedapi.kavin.rocks",
        "type": "piped",
        "score": 30,
        "latency": "209ms",
        "cors": false,
        "last_updated": "2026-05-05 20:07:00"
    },
    {
        "url": "https://inv.nadeko.net",
        "type": "invidious",
        "score": 15,
        "latency": "507ms",
        "cors": false,
        "last_updated": "2026-05-05 20:06:50"
    },
    {
        "url": "https://invidious.tiekoetter.com",
        "type": "invidious",
        "score": 15,
        "latency": "882ms",
        "cors": false,
        "last_updated": "2026-05-05 20:06:53"
    },
    {
        "url": "https://invidious.reallyaweso.me",
        "type": "invidious",
        "score": 15,
        "latency": "542ms",
        "cors": false,
        "last_updated": "2026-05-05 20:06:54"
    },
    {
        "url": "https://invidious.nerdvpn.de",
        "type": "invidious",
        "score": 15,
        "latency": "860ms",
        "cors": false,
        "last_updated": "2026-05-05 20:06:55"
    },
    {
        "url": "https://yewtu.be",
        "type": "invidious",
        "score": 15,
        "latency": "937ms",
        "cors": false,
        "last_updated": "2026-05-05 20:06:56"
    }
]