[
    {
        "url": "https://yt.omada.cafe",
        "type": "invidious",
        "score": 70,
        "latency": "2439ms",
        "cors": true,
        "last_updated": "2026-03-11 01:58:11"
    },
    {
        "url": "https://invidious.darkness.services",
        "type": "invidious",
        "score": 70,
        "latency": "2176ms",
        "cors": true,
        "last_updated": "2026-03-11 01:58:15"
    },
    {
        "url": "https://pipedapi.wireway.ch",
        "type": "piped",
        "score": 70,
        "latency": "1557ms",
        "cors": true,
        "last_updated": "2026-03-11 01:58:19"
    },
    {
        "url": "https://invidious.f5.si",
        "type": "invidious",
        "score": 30,
        "latency": "294ms",
        "cors": false,
        "last_updated": "2026-03-11 01:58:15"
    },
    {
        "url": "https://invidious.materialio.us",
        "type": "invidious",
        "score": 30,
        "latency": "452ms",
        "cors": false,
        "last_updated": "2026-03-11 01:58:16"
    },
    {
        "url": "https://pipedapi.kavin.rocks",
        "type": "piped",
        "score": 30,
        "latency": "101ms",
        "cors": false,
        "last_updated": "2026-03-11 01:58:17"
    },
    {
        "url": "https://inv.nadeko.net",
        "type": "invidious",
        "score": 15,
        "latency": "517ms",
        "cors": false,
        "last_updated": "2026-03-11 01:57:42"
    },
    {
        "url": "https://iv.melmac.space",
        "type": "invidious",
        "score": 15,
        "latency": "969ms",
        "cors": false,
        "last_updated": "2026-03-11 01:57:57"
    },
    {
        "url": "https://invidious.tiekoetter.com",
        "type": "invidious",
        "score": 15,
        "latency": "902ms",
        "cors": false,
        "last_updated": "2026-03-11 01:58:08"
    },
    {
        "url": "https://invidious.reallyaweso.me",
        "type": "invidious",
        "score": 15,
        "latency": "525ms",
        "cors": false,
        "last_updated": "2026-03-11 01:58:09"
    },
    {
        "url": "https://invidious.nerdvpn.de",
        "type": "invidious",
        "score": 15,
        "latency": "865ms",
        "cors": false,
        "last_updated": "2026-03-11 01:58:12"
    },
    {
        "url": "https://yewtu.be",
        "type": "invidious",
        "score": 15,
        "latency": "974ms",
        "cors": false,
        "last_updated": "2026-03-11 01:58:13"
    },
    {
        "url": "https://echostreamz.com",
        "type": "invidious",
        "score": 15,
        "latency": "827ms",
        "cors": false,
        "last_updated": "2026-03-11 01:58:17"
    },
    {
        "url": "https://api.piped.private.coffee",
        "type": "piped",
        "score": 15,
        "latency": "1291ms",
        "cors": false,
        "last_updated": "2026-03-11 01:58:18"
    },
    {
        "url": "https://pipedapi.dedyn.io",
        "type": "piped",
        "score": 15,
        "latency": "654ms",
        "cors": false,
        "last_updated": "2026-03-11 01:58:20"
    }
]