[
    {
        "url": "https://pipedapi.wireway.ch",
        "type": "piped",
        "score": 100,
        "latency": "383ms",
        "cors": true,
        "last_updated": "2026-06-06 20:08:38"
    },
    {
        "url": "https://yt.omada.cafe",
        "type": "invidious",
        "score": 85,
        "latency": "728ms",
        "cors": true,
        "last_updated": "2026-06-06 20:08:23"
    },
    {
        "url": "https://api.piped.private.coffee",
        "type": "piped",
        "score": 85,
        "latency": "825ms",
        "cors": true,
        "last_updated": "2026-06-06 20:08:37"
    },
    {
        "url": "https://pipedapi.dedyn.io",
        "type": "piped",
        "score": 70,
        "latency": "1685ms",
        "cors": true,
        "last_updated": "2026-06-06 20:08:40"
    },
    {
        "url": "https://inv.nadeko.net",
        "type": "invidious",
        "score": 30,
        "latency": "489ms",
        "cors": false,
        "last_updated": "2026-06-06 20:08:16"
    },
    {
        "url": "https://yt.vern.cc",
        "type": "invidious",
        "score": 30,
        "latency": "108ms",
        "cors": false,
        "last_updated": "2026-06-06 20:08:21"
    },
    {
        "url": "https://invidious.reallyaweso.me",
        "type": "invidious",
        "score": 30,
        "latency": "373ms",
        "cors": false,
        "last_updated": "2026-06-06 20:08:22"
    },
    {
        "url": "https://pipedapi.kavin.rocks",
        "type": "piped",
        "score": 30,
        "latency": "282ms",
        "cors": false,
        "last_updated": "2026-06-06 20:08:37"
    },
    {
        "url": "https://invidious.tiekoetter.com",
        "type": "invidious",
        "score": 15,
        "latency": "809ms",
        "cors": false,
        "last_updated": "2026-06-06 20:08:22"
    },
    {
        "url": "https://invidious.nerdvpn.de",
        "type": "invidious",
        "score": 15,
        "latency": "595ms",
        "cors": false,
        "last_updated": "2026-06-06 20:08:24"
    },
    {
        "url": "https://yewtu.be",
        "type": "invidious",
        "score": 15,
        "latency": "983ms",
        "cors": false,
        "last_updated": "2026-06-06 20:08:25"
    },
    {
        "url": "https://invidious.darkness.services",
        "type": "invidious",
        "score": 15,
        "latency": "510ms",
        "cors": false,
        "last_updated": "2026-06-06 20:08:25"
    },
    {
        "url": "https://invidious.f5.si",
        "type": "invidious",
        "score": 15,
        "latency": "543ms",
        "cors": false,
        "last_updated": "2026-06-06 20:08:26"
    },
    {
        "url": "https://invidious.materialio.us",
        "type": "invidious",
        "score": 15,
        "latency": "537ms",
        "cors": false,
        "last_updated": "2026-06-06 20:08:26"
    }
]