[
    {
        "url": "https://yt.omada.cafe",
        "type": "invidious",
        "score": 100,
        "latency": "310ms",
        "cors": true,
        "last_updated": "2026-04-13 21:50:06"
    },
    {
        "url": "https://invidious.darkness.services",
        "type": "invidious",
        "score": 100,
        "latency": "339ms",
        "cors": true,
        "last_updated": "2026-04-13 21:50:07"
    },
    {
        "url": "https://pipedapi.wireway.ch",
        "type": "piped",
        "score": 100,
        "latency": "411ms",
        "cors": true,
        "last_updated": "2026-04-13 21:50:11"
    },
    {
        "url": "https://invidious.f5.si",
        "type": "invidious",
        "score": 85,
        "latency": "653ms",
        "cors": true,
        "last_updated": "2026-04-13 21:50:08"
    },
    {
        "url": "https://api.piped.private.coffee",
        "type": "piped",
        "score": 85,
        "latency": "1090ms",
        "cors": true,
        "last_updated": "2026-04-13 21:50:10"
    },
    {
        "url": "https://pipedapi.dedyn.io",
        "type": "piped",
        "score": 85,
        "latency": "617ms",
        "cors": true,
        "last_updated": "2026-04-13 21:50:11"
    },
    {
        "url": "https://invidious.reallyaweso.me",
        "type": "invidious",
        "score": 30,
        "latency": "431ms",
        "cors": false,
        "last_updated": "2026-04-13 21:50:05"
    },
    {
        "url": "https://pipedapi.kavin.rocks",
        "type": "piped",
        "score": 30,
        "latency": "147ms",
        "cors": false,
        "last_updated": "2026-04-13 21:50:09"
    },
    {
        "url": "https://inv.nadeko.net",
        "type": "invidious",
        "score": 15,
        "latency": "501ms",
        "cors": false,
        "last_updated": "2026-04-13 21:50:00"
    },
    {
        "url": "https://iv.melmac.space",
        "type": "invidious",
        "score": 15,
        "latency": "756ms",
        "cors": false,
        "last_updated": "2026-04-13 21:50:03"
    },
    {
        "url": "https://yt.vern.cc",
        "type": "invidious",
        "score": 15,
        "latency": "1244ms",
        "cors": false,
        "last_updated": "2026-04-13 21:50:04"
    },
    {
        "url": "https://invidious.tiekoetter.com",
        "type": "invidious",
        "score": 15,
        "latency": "739ms",
        "cors": false,
        "last_updated": "2026-04-13 21:50:05"
    },
    {
        "url": "https://invidious.nerdvpn.de",
        "type": "invidious",
        "score": 15,
        "latency": "600ms",
        "cors": false,
        "last_updated": "2026-04-13 21:50:06"
    },
    {
        "url": "https://yewtu.be",
        "type": "invidious",
        "score": 15,
        "latency": "854ms",
        "cors": false,
        "last_updated": "2026-04-13 21:50:07"
    },
    {
        "url": "https://invidious.materialio.us",
        "type": "invidious",
        "score": 15,
        "latency": "554ms",
        "cors": false,
        "last_updated": "2026-04-13 21:50:09"
    },
    {
        "url": "https://echostreamz.com",
        "type": "invidious",
        "score": 15,
        "latency": "571ms",
        "cors": false,
        "last_updated": "2026-04-13 21:50:09"
    }
]