[
    {
        "url": "https://pipedapi.wireway.ch",
        "type": "piped",
        "score": 85,
        "latency": "588ms",
        "cors": true,
        "last_updated": "2026-02-28 17:45:10"
    },
    {
        "url": "https://yt.omada.cafe",
        "type": "invidious",
        "score": 70,
        "latency": "3055ms",
        "cors": true,
        "last_updated": "2026-02-28 17:45:03"
    },
    {
        "url": "https://inv.nadeko.net",
        "type": "invidious",
        "score": 30,
        "latency": "479ms",
        "cors": false,
        "last_updated": "2026-02-28 17:44:34"
    },
    {
        "url": "https://invidious.materialio.us",
        "type": "invidious",
        "score": 30,
        "latency": "438ms",
        "cors": false,
        "last_updated": "2026-02-28 17:45:07"
    },
    {
        "url": "https://pipedapi.kavin.rocks",
        "type": "piped",
        "score": 30,
        "latency": "271ms",
        "cors": false,
        "last_updated": "2026-02-28 17:45:08"
    },
    {
        "url": "https://invidious.tiekoetter.com",
        "type": "invidious",
        "score": 15,
        "latency": "787ms",
        "cors": false,
        "last_updated": "2026-02-28 17:45:00"
    },
    {
        "url": "https://invidious.reallyaweso.me",
        "type": "invidious",
        "score": 15,
        "latency": "564ms",
        "cors": false,
        "last_updated": "2026-02-28 17:45:00"
    },
    {
        "url": "https://invidious.nerdvpn.de",
        "type": "invidious",
        "score": 15,
        "latency": "782ms",
        "cors": false,
        "last_updated": "2026-02-28 17:45:04"
    },
    {
        "url": "https://yewtu.be",
        "type": "invidious",
        "score": 15,
        "latency": "1091ms",
        "cors": false,
        "last_updated": "2026-02-28 17:45:05"
    },
    {
        "url": "https://invidious.f5.si",
        "type": "invidious",
        "score": 15,
        "latency": "596ms",
        "cors": false,
        "last_updated": "2026-02-28 17:45:07"
    },
    {
        "url": "https://echostreamz.com",
        "type": "invidious",
        "score": 15,
        "latency": "811ms",
        "cors": false,
        "last_updated": "2026-02-28 17:45:08"
    },
    {
        "url": "https://api.piped.private.coffee",
        "type": "piped",
        "score": 15,
        "latency": "1273ms",
        "cors": false,
        "last_updated": "2026-02-28 17:45:10"
    },
    {
        "url": "https://pipedapi.dedyn.io",
        "type": "piped",
        "score": 15,
        "latency": "626ms",
        "cors": false,
        "last_updated": "2026-02-28 17:45:11"
    }
]