[
    {
        "url": "https://invidious.f5.si",
        "type": "invidious",
        "score": 100,
        "latency": "489ms",
        "cors": true,
        "last_updated": "2026-04-05 06:42:21"
    },
    {
        "url": "https://echostreamz.com",
        "type": "invidious",
        "score": 70,
        "latency": "1942ms",
        "cors": true,
        "last_updated": "2026-04-05 06:42:24"
    },
    {
        "url": "https://api.piped.private.coffee",
        "type": "piped",
        "score": 70,
        "latency": "1735ms",
        "cors": true,
        "last_updated": "2026-04-05 06:42:26"
    },
    {
        "url": "https://pipedapi.dedyn.io",
        "type": "piped",
        "score": 70,
        "latency": "2066ms",
        "cors": true,
        "last_updated": "2026-04-05 06:42:38"
    },
    {
        "url": "https://inv.nadeko.net",
        "type": "invidious",
        "score": 30,
        "latency": "497ms",
        "cors": false,
        "last_updated": "2026-04-05 06:41:43"
    },
    {
        "url": "https://invidious.reallyaweso.me",
        "type": "invidious",
        "score": 30,
        "latency": "480ms",
        "cors": false,
        "last_updated": "2026-04-05 06:42:06"
    },
    {
        "url": "https://invidious.materialio.us",
        "type": "invidious",
        "score": 30,
        "latency": "429ms",
        "cors": false,
        "last_updated": "2026-04-05 06:42:22"
    },
    {
        "url": "https://pipedapi.kavin.rocks",
        "type": "piped",
        "score": 30,
        "latency": "456ms",
        "cors": false,
        "last_updated": "2026-04-05 06:42:24"
    },
    {
        "url": "https://iv.melmac.space",
        "type": "invidious",
        "score": 15,
        "latency": "874ms",
        "cors": false,
        "last_updated": "2026-04-05 06:41:54"
    },
    {
        "url": "https://invidious.tiekoetter.com",
        "type": "invidious",
        "score": 15,
        "latency": "912ms",
        "cors": false,
        "last_updated": "2026-04-05 06:42:05"
    },
    {
        "url": "https://invidious.nerdvpn.de",
        "type": "invidious",
        "score": 15,
        "latency": "925ms",
        "cors": false,
        "last_updated": "2026-04-05 06:42:18"
    },
    {
        "url": "https://yewtu.be",
        "type": "invidious",
        "score": 15,
        "latency": "1018ms",
        "cors": false,
        "last_updated": "2026-04-05 06:42:19"
    }
]