[
    {
        "url": "https://invidious.f5.si",
        "type": "invidious",
        "score": 85,
        "latency": "613ms",
        "cors": true,
        "last_updated": "2026-04-04 15:31:43"
    },
    {
        "url": "https://api.piped.private.coffee",
        "type": "piped",
        "score": 85,
        "latency": "805ms",
        "cors": true,
        "last_updated": "2026-04-04 15:31:46"
    },
    {
        "url": "https://pipedapi.dedyn.io",
        "type": "piped",
        "score": 85,
        "latency": "528ms",
        "cors": true,
        "last_updated": "2026-04-04 15:31:57"
    },
    {
        "url": "https://yt.omada.cafe",
        "type": "invidious",
        "score": 70,
        "latency": "2477ms",
        "cors": true,
        "last_updated": "2026-04-04 15:31:38"
    },
    {
        "url": "https://echostreamz.com",
        "type": "invidious",
        "score": 70,
        "latency": "1643ms",
        "cors": true,
        "last_updated": "2026-04-04 15:31:45"
    },
    {
        "url": "https://inv.nadeko.net",
        "type": "invidious",
        "score": 30,
        "latency": "444ms",
        "cors": false,
        "last_updated": "2026-04-04 15:31:06"
    },
    {
        "url": "https://invidious.reallyaweso.me",
        "type": "invidious",
        "score": 30,
        "latency": "425ms",
        "cors": false,
        "last_updated": "2026-04-04 15:31:36"
    },
    {
        "url": "https://pipedapi.kavin.rocks",
        "type": "piped",
        "score": 30,
        "latency": "204ms",
        "cors": false,
        "last_updated": "2026-04-04 15:31:45"
    },
    {
        "url": "https://iv.melmac.space",
        "type": "invidious",
        "score": 15,
        "latency": "686ms",
        "cors": false,
        "last_updated": "2026-04-04 15:31:21"
    },
    {
        "url": "https://invidious.tiekoetter.com",
        "type": "invidious",
        "score": 15,
        "latency": "577ms",
        "cors": false,
        "last_updated": "2026-04-04 15:31:35"
    },
    {
        "url": "https://invidious.nerdvpn.de",
        "type": "invidious",
        "score": 15,
        "latency": "547ms",
        "cors": false,
        "last_updated": "2026-04-04 15:31:39"
    },
    {
        "url": "https://yewtu.be",
        "type": "invidious",
        "score": 15,
        "latency": "799ms",
        "cors": false,
        "last_updated": "2026-04-04 15:31:40"
    },
    {
        "url": "https://invidious.materialio.us",
        "type": "invidious",
        "score": 15,
        "latency": "560ms",
        "cors": false,
        "last_updated": "2026-04-04 15:31:43"
    }
]