[
    {
        "url": "https://api.piped.private.coffee",
        "type": "piped",
        "score": 85,
        "latency": "1349ms",
        "cors": true,
        "last_updated": "2026-06-26 15:38:20"
    },
    {
        "url": "https://pipedapi.wireway.ch",
        "type": "piped",
        "score": 70,
        "latency": "3025ms",
        "cors": true,
        "last_updated": "2026-06-26 15:38:23"
    },
    {
        "url": "https://pipedapi.dedyn.io",
        "type": "piped",
        "score": 70,
        "latency": "2056ms",
        "cors": true,
        "last_updated": "2026-06-26 15:38:25"
    },
    {
        "url": "https://inv.vern.cc",
        "type": "invidious",
        "score": 30,
        "latency": "331ms",
        "cors": false,
        "last_updated": "2026-06-26 15:38:08"
    },
    {
        "url": "https://yt.vern.cc",
        "type": "invidious",
        "score": 30,
        "latency": "294ms",
        "cors": false,
        "last_updated": "2026-06-26 15:38:09"
    },
    {
        "url": "https://invidious.materialio.us",
        "type": "invidious",
        "score": 30,
        "latency": "475ms",
        "cors": false,
        "last_updated": "2026-06-26 15:38:18"
    },
    {
        "url": "https://pipedapi.kavin.rocks",
        "type": "piped",
        "score": 30,
        "latency": "399ms",
        "cors": false,
        "last_updated": "2026-06-26 15:38:19"
    },
    {
        "url": "https://inv.nadeko.net",
        "type": "invidious",
        "score": 15,
        "latency": "532ms",
        "cors": false,
        "last_updated": "2026-06-26 15:38:08"
    },
    {
        "url": "https://invidious.tiekoetter.com",
        "type": "invidious",
        "score": 15,
        "latency": "717ms",
        "cors": false,
        "last_updated": "2026-06-26 15:38:10"
    },
    {
        "url": "https://invidious.reallyaweso.me",
        "type": "invidious",
        "score": 15,
        "latency": "559ms",
        "cors": false,
        "last_updated": "2026-06-26 15:38:10"
    },
    {
        "url": "https://invidious.nerdvpn.de",
        "type": "invidious",
        "score": 15,
        "latency": "906ms",
        "cors": false,
        "last_updated": "2026-06-26 15:38:14"
    },
    {
        "url": "https://yewtu.be",
        "type": "invidious",
        "score": 15,
        "latency": "1382ms",
        "cors": false,
        "last_updated": "2026-06-26 15:38:16"
    },
    {
        "url": "https://invidious.darkness.services",
        "type": "invidious",
        "score": 15,
        "latency": "727ms",
        "cors": false,
        "last_updated": "2026-06-26 15:38:16"
    },
    {
        "url": "https://invidious.f5.si",
        "type": "invidious",
        "score": 15,
        "latency": "719ms",
        "cors": false,
        "last_updated": "2026-06-26 15:38:17"
    },
    {
        "url": "https://echostreamz.com",
        "type": "invidious",
        "score": 15,
        "latency": "595ms",
        "cors": false,
        "last_updated": "2026-06-26 15:38:18"
    }
]